py3tftp/__init__.py
py3tftp/__main__.py
py3tftp/cli_parser.py
py3tftp/exceptions.py
py3tftp/file_io.py
py3tftp/netascii.py
py3tftp/protocols.py
py3tftp/tftp_packet.py
py3tftp/tftp_parsing.py
py3tftp-1.3.0.dist-info/LICENSE
py3tftp-1.3.0.dist-info/LICENSE2
py3tftp-1.3.0.dist-info/LICENSET
py3tftp-1.3.0.dist-info/LICENSE_TEST
py3tftp-1.3.0.dist-info/METADATA
py3tftp-1.3.0.dist-info/WHEEL
py3tftp-1.3.0.dist-info/entry_points.txt
py3tftp-1.3.0.dist-info/top_level.txt
py3tftp-1.3.0.dist-info/RECORD
