Metadata-Version: 2.1
Name: py3tftp
Version: 1.3.0
Summary: Python 3 asynchronous TFTP server.
Home-page: http://github.com/sirMackk/py3tftp
Author: Matt O.
Author-email: matt@mattscodecave.com
License: MIT
Keywords: async asynchronous tftp
Platform: UNKNOWN
Classifier: Development Status :: 5 - Production/Stable
Classifier: Intended Audience :: Developers
Classifier: Intended Audience :: System Administrators
Classifier: Programming Language :: Python :: 3 :: Only
Classifier: Programming Language :: Python :: 3.5
Classifier: Programming Language :: Python :: 3.6
Classifier: Programming Language :: Python :: 3.7
Classifier: Programming Language :: Python :: 3.8
Classifier: Programming Language :: Python :: 3.9
Classifier: Topic :: Utilities
Classifier: Topic :: Software Development
Classifier: License :: OSI Approved :: MIT License
